magika/__init__.py
magika/colors.py
magika/logger.py
magika/magika.py
magika/py.typed
magika/cli/magika_client.py
magika/cli/magika_rust_client_not_found_warning.py
magika/config/content_types_kb.min.json
magika/models/standard_v3_3/README.md
magika/models/standard_v3_3/config.min.json
magika/models/standard_v3_3/metadata.json
magika/models/standard_v3_3/model.onnx
magika/types/__init__.py
magika/types/content_type_info.py
magika/types/content_type_label.py
magika/types/magika_error.py
magika/types/magika_prediction.py
magika/types/magika_result.py
magika/types/model.py
magika/types/overwrite_reason.py
magika/types/prediction_mode.py
magika/types/seekable.py
magika/types/status.py
magika/types/strenum.py
magika-0.6.2.dist-info/METADATA
magika-0.6.2.dist-info/WHEEL
magika-0.6.2.dist-info/entry_points.txt
magika-0.6.2.dist-info/RECORD
