Metadata-Version: 2.4
Name: magika
Version: 0.6.2
Summary: A tool to determine the content type of a file with deep learning
Project-URL: Homepage, https://github.com/google/magika
Project-URL: Documentation, https://github.com/google/magika/blob/main/python/README.md
Project-URL: Repository, https://github.com/google/magika/
Project-URL: Issues, https://github.com/google/magika/issues
Project-URL: Changelog, https://github.com/google/magika/blob/main/python/CHANGELOG.md
Author-email: Magika Developers <magika-dev@google.com>
License: Apache-2.0
Keywords: content type detection,machine learning
Classifier: Development Status :: 5 - Production/Stable
Classifier: Environment :: Console
Classifier: Intended Audience :: Developers
Classifier: Intended Audience :: Science/Research
Classifier: Intended Audience :: System Administrators
Classifier: License :: OSI Approved :: Apache Software License
Classifier: Operating System :: MacOS
Classifier: Operating System :: Microsoft :: Windows
Classifier: Operating System :: Unix
Classifier: Programming Language :: Python
Classifier: Programming Language :: Python :: 3
Classifier: Programming Language :: Python :: 3.8
Classifier: Programming Language :: Python :: 3.9
Classifier: Programming Language :: Python :: 3.10
Classifier: Programming Language :: Python :: 3.11
Classifier: Programming Language :: Python :: 3.12
Classifier: Programming Language :: Python :: 3.13
Classifier: Topic :: Scientific/Engineering :: Artificial Intelligence
Classifier: Topic :: Security
Classifier: Topic :: Software Development
Classifier: Typing :: Typed
Requires-Python: >=3.8
Requires-Dist: click>=8.1.7
Requires-Dist: numpy>=1.24; python_version < '3.12'
Requires-Dist: numpy>=1.26; python_version >= '3.12' and python_version < '3.13'
Requires-Dist: numpy>=2.1.0; python_version >= '3.13'
Requires-Dist: onnxruntime<1.20.0,>=1.17.0; python_version <= '3.9'
Requires-Dist: onnxruntime>=1.17.0; python_version > '3.9'
Requires-Dist: python-dotenv>=1.0.1
